MANIFEST.in
README.rst
setup.py
ubuntudesign/__init__.py
ubuntudesign.gsa.egg-info/PKG-INFO
ubuntudesign.gsa.egg-info/SOURCES.txt
ubuntudesign.gsa.egg-info/dependency_links.txt
ubuntudesign.gsa.egg-info/requires.txt
ubuntudesign.gsa.egg-info/top_level.txt
ubuntudesign/gsa/__init__.py
ubuntudesign/gsa/views.py