Metadata-Version: 1.0
Name: ubuntudesign.gsa
Version: 1.1.0
Summary: A client for communicating with the Google Search Appliance.
Home-page: https://github.com/ubuntudesign/python-gsa
Author: Canonical webteam
Author-email: robin+pypi@canonical.com
License: UNKNOWN
Platform: UNKNOWN
